vtk_openCARP_methods_ibt/__init__.py
vtk_openCARP_methods_ibt/writer.py
vtk_openCARP_methods_ibt/AugmentA_methods/__init__.py
vtk_openCARP_methods_ibt/AugmentA_methods/point_selection.py
vtk_openCARP_methods_ibt/AugmentA_methods/vtk_operations.py
vtk_openCARP_methods_ibt/carputils_commands/abstract_command.py
vtk_openCARP_methods_ibt/carputils_commands/lat_command.py
vtk_openCARP_methods_ibt/mathematical_operations/__init__.py
vtk_openCARP_methods_ibt/mathematical_operations/vector_operations.py
vtk_openCARP_methods_ibt/openCARP/__init__.py
vtk_openCARP_methods_ibt/openCARP/exporting.py
vtk_openCARP_methods_ibt/openCARP/importing.py
vtk_openCARP_methods_ibt/quick_fixes/__init__.py
vtk_openCARP_methods_ibt/quick_fixes/mapping.py
vtk_openCARP_methods_ibt/vtk_methods/__init__.py
vtk_openCARP_methods_ibt/vtk_methods/converters.py
vtk_openCARP_methods_ibt/vtk_methods/dat_to_vtk_conversion.py
vtk_openCARP_methods_ibt/vtk_methods/exporting.py
vtk_openCARP_methods_ibt/vtk_methods/filters.py
vtk_openCARP_methods_ibt/vtk_methods/finder.py
vtk_openCARP_methods_ibt/vtk_methods/helper_methods.py
vtk_openCARP_methods_ibt/vtk_methods/init_objects.py
vtk_openCARP_methods_ibt/vtk_methods/mapper.py
vtk_openCARP_methods_ibt/vtk_methods/normal_orientation.py
vtk_openCARP_methods_ibt/vtk_methods/reader.py
vtk_openCARP_methods_ibt/vtk_methods/thresholding.py
vtk_opencarp_methods_ibt-1.0.4.dist-info/METADATA
vtk_opencarp_methods_ibt-1.0.4.dist-info/WHEEL
vtk_opencarp_methods_ibt-1.0.4.dist-info/licenses/LICENSE
vtk_opencarp_methods_ibt-1.0.4.dist-info/RECORD
